CHANGELOG.md
MANIFEST.in
README.md
setup.cfg
setup.py
pip_services3_azure/__init__.py
pip_services3_azure.egg-info/PKG-INFO
pip_services3_azure.egg-info/SOURCES.txt
pip_services3_azure.egg-info/dependency_links.txt
pip_services3_azure.egg-info/requires.txt
pip_services3_azure.egg-info/top_level.txt
pip_services3_azure.egg-info/zip-safe
pip_services3_azure/clients/AzureFunctionClient.py
pip_services3_azure/clients/CommandableAzureFunctionClient.py
pip_services3_azure/clients/__init__.py
pip_services3_azure/connect/AzureConnectionParams.py
pip_services3_azure/connect/AzureConnectionResolver.py
pip_services3_azure/connect/__init__.py
pip_services3_azure/containers/AzureFunction.py
pip_services3_azure/containers/AzureFunctionContextHelper.py
pip_services3_azure/containers/CommandableAzureFunction.py
pip_services3_azure/containers/__init__.py
pip_services3_azure/services/AzureFunctionAction.py
pip_services3_azure/services/AzureFunctionService.py
pip_services3_azure/services/CommandableAzureFunctionService.py
pip_services3_azure/services/IAzureFunctionService.py
pip_services3_azure/services/__init__.py
test/clients/DummyAzureFunctionClient.py
test/clients/DummyClientFixture.py
test/clients/DummyCommandableAzureFunctionClient.py
test/clients/__init__.py
test/clients/test_DummyAzureFunctionClient.py
test/clients/test_DummyCommandableAzureFunctionClient.py
test/connect/__init__.py
test/connect/test_AzureConnectionParams.py
test/containers/DummyAzureFunction.py
test/containers/DummyAzureFuntionFixture.py
test/containers/DummyCommandableAzureFunction.py
test/containers/__init__.py
test/containers/test_DummyAzureFunction.py
test/containers/test_DummyCommandableAzureFunction.py
test/services/DummyAzureFunction.py
test/services/DummyAzureFunctionService.py
test/services/DummyAzureFunctionServiceFixture.py
test/services/DummyCommandableAzureFunctionService.py
test/services/__init__.py
test/services/test_DummyAzureFunctionService.py
test/services/test_DummyCommandableAzureFunctionService.py